MANIFEST.in
README.rst
requirements.txt
setup.cfg
setup.py
kotti_theme_sbadmin/__init__.py
kotti_theme_sbadmin/__init__.pyc
kotti_theme_sbadmin/fanstatic.py
kotti_theme_sbadmin/fanstatic.pyc
kotti_theme_sbadmin/resources.pyc
kotti_theme_sbadmin.egg-info/PKG-INFO
kotti_theme_sbadmin.egg-info/SOURCES.txt
kotti_theme_sbadmin.egg-info/dependency_links.txt
kotti_theme_sbadmin.egg-info/entry_points.txt
kotti_theme_sbadmin.egg-info/not-zip-safe
kotti_theme_sbadmin.egg-info/requires.txt
kotti_theme_sbadmin.egg-info/top_level.txt
kotti_theme_sbadmin/locale/.gitkeep
kotti_theme_sbadmin/overrides/kotti/templates/add-dropdown.pt
kotti_theme_sbadmin/overrides/kotti/templates/editor-bar.pt
kotti_theme_sbadmin/overrides/kotti/templates/forbidden.pt
kotti_theme_sbadmin/overrides/kotti/templates/login.pt
kotti_theme_sbadmin/overrides/kotti/templates/user-nav-bar.pt
kotti_theme_sbadmin/overrides/kotti/templates/edit/master.pt
kotti_theme_sbadmin/overrides/kotti/templates/http-errors/notfound.pt
kotti_theme_sbadmin/overrides/kotti/templates/site-setup/master.pt
kotti_theme_sbadmin/overrides/kotti/templates/view/footer.pt
kotti_theme_sbadmin/overrides/kotti/templates/view/master.pt
kotti_theme_sbadmin/overrides/kotti/templates/view/nav.pt
kotti_theme_sbadmin/overrides/kotti/templates/view/search.pt
kotti_theme_sbadmin/static/scripts.js
kotti_theme_sbadmin/static/scripts.min.js
kotti_theme_sbadmin/static/styles.css
kotti_theme_sbadmin/static/styles.min.css
kotti_theme_sbadmin/static/css/animate.css
kotti_theme_sbadmin/static/css/bootstrap.min.css
kotti_theme_sbadmin/static/css/sidebar.css
kotti_theme_sbadmin/static/css/style.css
kotti_theme_sbadmin/static/css/patterns/3.png
kotti_theme_sbadmin/static/css/patterns/4.png
kotti_theme_sbadmin/static/css/patterns/header-profile-skin-1.png
kotti_theme_sbadmin/static/css/patterns/header-profile-skin-2.png
kotti_theme_sbadmin/static/css/patterns/header-profile-skin-3.png
kotti_theme_sbadmin/static/css/patterns/header-profile.png
kotti_theme_sbadmin/static/css/patterns/shattered.png
kotti_theme_sbadmin/static/css/plugins/awesome-bootstrap-checkbox/awesome-bootstrap-checkbox.css
kotti_theme_sbadmin/static/css/plugins/blueimp/css/blueimp-gallery.min.css
kotti_theme_sbadmin/static/css/plugins/blueimp/img/error.png
